<?xml version="1.0" encoding="utf-8"?>
<odoo>
    <!-- chưa có add vào file __manifest__ -->
    <template id="cart_delivery" name="Delivery Costs" inherit_id="website_sale.total">
        <xpath expr="//tr[@id='order_total_untaxed']" position="before">
            <tr id="order_delivery" t-if="website_sale_order and website_sale_order.carrier_id">
              <td class="text-right border-0 text-muted"  title="Delivery will be updated after choosing a new delivery method">Delivery:</td>
              <td class="text-xl-right border-0 text-muted" >
                   <span t-field="website_sale_order.amount_delivery" class="monetary_field" style="white-space: nowrap;" t-options='{
                      "widget": "monetary",
                      "display_currency": website_sale_order.currency_id,
                  }'/>
              </td>
            </tr>
        </xpath>
    </template>
</odoo>
